spf_ctrl/PhotoFrame.py
spf_ctrl/__init__.py
spf_ctrl/__main__.py
spf_ctrl-0.1.1.dist-info/LICENSE
spf_ctrl-0.1.1.dist-info/METADATA
spf_ctrl-0.1.1.dist-info/WHEEL
spf_ctrl-0.1.1.dist-info/top_level.txt
spf_ctrl-0.1.1.dist-info/RECORD
