Metadata-Version: 2.1
Name: spf-ctrl
Version: 0.1.1
Summary: send images to Samsung photo frames from python
Home-page: https://github.com/erictroebs/spf_ctrl
Author: Eric Tröbs
Project-URL: Bug Tracker, https://github.com/erictroebs/spf_ctrl/issues
Classifier: Programming Language :: Python :: 3
Classifier: License :: OSI Approved :: Apache Software License
Requires-Python: >=3.6
License-File: LICENSE
Requires-Dist: pyusb (~=1.2.1)
